F1_lap_time_telementary/testing.py
f1_lap_time_telementary-0.2.0.dist-info/licenses/LICENSE
f1_lap_time_telementary-0.2.0.dist-info/METADATA
f1_lap_time_telementary-0.2.0.dist-info/WHEEL
f1_lap_time_telementary-0.2.0.dist-info/top_level.txt
f1_lap_time_telementary-0.2.0.dist-info/RECORD
