Metadata-Version: 2.4
Name: F1_lap_time_telementary
Version: 0.2.0
Summary: Plot F1 telemetry data using FastF1
Author-email: Sidhartha Kumar <siddkumar718@gmail.com>
License-Expression: MIT
License-File: LICENSE
Requires-Dist: fastf1>=3.0.0
Requires-Dist: matplotlib>=3.0
Dynamic: license-file
